BoostCKu/README.md
BoostCKu/__init__.py
BoostCKu/__main__.py
BoostCKu/file.epub
BoostCKu/index.html
BoostCKu/css/__init__.py
BoostCKu/css/annotations.css
BoostCKu/css/main.css
BoostCKu/css/normalize.css
BoostCKu/css/popup.css
BoostCKu/font/__init__.py
BoostCKu/font/fontello.eot
BoostCKu/font/fontello.svg
BoostCKu/font/fontello.ttf
BoostCKu/font/fontello.woff
BoostCKu/img/__init__.py
BoostCKu/img/annotator-glyph-sprite.png
BoostCKu/img/annotator-icon-sprite.png
BoostCKu/img/apple-touch-icon.png
BoostCKu/img/cancelfullscreen.png
BoostCKu/img/close.png
BoostCKu/img/fullscreen.png
BoostCKu/img/loader.gif
BoostCKu/img/menu-icon.png
BoostCKu/img/save.png
BoostCKu/img/saved.png
BoostCKu/img/settings-s.png
BoostCKu/img/settings.png
BoostCKu/img/star.png
BoostCKu/js/__init__.py
BoostCKu/js/epub.js
BoostCKu/js/epub.min.js
BoostCKu/js/epub.min.map
BoostCKu/js/hooks.min.js
BoostCKu/js/hooks.min.map
BoostCKu/js/reader.js
BoostCKu/js/reader.js.map
BoostCKu/js/reader.min.js
BoostCKu/js/reader.min.map
BoostCKu/js/hooks/__init__.py
BoostCKu/js/hooks/extensions/__init__.py
BoostCKu/js/hooks/extensions/highlight.js
BoostCKu/js/libs/__init__.py
BoostCKu/js/libs/jquery.min.js
BoostCKu/js/libs/localforage.min.js
BoostCKu/js/libs/screenfull.js
BoostCKu/js/libs/screenfull.min.js
BoostCKu/js/libs/zip.min.js
BoostCKu/js/plugins/__init__.py
BoostCKu/js/plugins/hypothesis.js
BoostCKu/js/plugins/search.js
boost_c_ku-2024.3.1.0.dist-info/METADATA
boost_c_ku-2024.3.1.0.dist-info/WHEEL
boost_c_ku-2024.3.1.0.dist-info/entry_points.txt
boost_c_ku-2024.3.1.0.dist-info/top_level.txt
boost_c_ku-2024.3.1.0.dist-info/RECORD
